pypokemon/__init__.py
pypokemon/__main__.py
pypokemon/pokemon.py
pypokemon-0.1.4.dist-info/licenses/LICENSE
pypokemon-0.1.4.dist-info/METADATA
pypokemon-0.1.4.dist-info/WHEEL
pypokemon-0.1.4.dist-info/entry_points.txt
pypokemon-0.1.4.dist-info/top_level.txt
pypokemon-0.1.4.dist-info/RECORD
