Metadata-Version: 2.4
Name: pypokemon
Version: 0.1.4
Summary: A turn-based Pokémon battle game with ASCII art.
Author-email: Chen Jun Hsu <ch4356@nyu.edu>, Kenny Pan <zp2165@nyu.edu>, Shenrui Xue <sx2218@nyu.edu>, Eric Zhao <zz4040@nyu.edu>
License:                     GNU GENERAL PUBLIC LICENSE
Project-URL: Homepage, https://github.com/software-students-spring2025/3-python-package-ez-squad-3-0
Project-URL: Repository, https://github.com/software-students-spring2025/3-python-package-ez-squad-3-0.git
Project-URL: Bug Tracker, https://github.com/software-students-spring2025/3-python-package-ez-squad-3-0/issues
Keywords: pokemon,game,battle,ascii
Classifier: Programming Language :: Python :: 3
Classifier: License :: OSI Approved :: MIT License
Classifier: Operating System :: OS Independent
Requires-Python: >=3.7
License-File: LICENSE
Provides-Extra: dev
Requires-Dist: pytest; extra == "dev"
Dynamic: license-file
